uart/uart.v
// uart example from https://learn.lushaylabs.com/tang-nano-series/
// mirac gulgonul - 2023
`default_nettype none

module uart #(
    parameter DELAY_FRAMES = 234  // 27MHz at 115_200 baudrate 
) (
    input clk,
    input uart_rx,
    output uart_tx,
    output reg [5:0] led,
    input btn1

);

  // RECEIVE
  localparam HALF_DELAY_WAIT = (DELAY_FRAMES / 2);
  localparam RX_STATE_IDLE = 0;
  localparam RX_STATE_START_BIT = 1;
  localparam RX_STATE_READ_WAIT = 2;
  localparam RX_STATE_READ = 3;
  localparam RX_STATE_STOP_BIT = 4;

  // receive state machine with 5 states
  // idle, start bit, read wait, read, stop bit
  reg [3:0] rx_state = 0;  // 6 states
  reg [12:0] rx_counter = 0;  // counting clock pulses
  reg [2:0] rx_bit_number = 0;  // how many bits read
  reg [7:0] data_in = 0;  // store the byte to be received
  reg byte_ready = 0;  // flag, high when data is ready

  // uart receive
  always @(posedge clk) begin
    case (rx_state)  // state machine case switch

      RX_STATE_IDLE: begin
        if (uart_rx == 0) begin
          rx_state <= RX_STATE_START_BIT;  // move to startbit state
          rx_counter <= 1;  // init counter
          rx_bit_number <= 0;  // 0 bits data read
          byte_ready <= 0;  // data not ready
        end
      end

      RX_STATE_START_BIT: begin
        if (rx_counter == HALF_DELAY_WAIT) begin
          rx_state   <= RX_STATE_READ_WAIT;
          rx_counter <= 1;
        end else rx_counter <= rx_counter + 1;
      end

      RX_STATE_READ_WAIT: begin
        rx_counter <= rx_counter + 1;
        if ((rx_counter + 1) == DELAY_FRAMES) begin
          rx_state <= RX_STATE_READ;
        end
      end

      RX_STATE_READ: begin
        rx_counter <= 1;
        // append received to data array
        data_in <= {uart_rx, data_in[7:1]};
        rx_bit_number <= rx_bit_number + 1;
        // try 'd7 instead?
        if (rx_bit_number == 3'b111) rx_state <= RX_STATE_STOP_BIT;
        else rx_state <= RX_STATE_READ_WAIT;
      end

      RX_STATE_STOP_BIT: begin
        rx_counter <= rx_counter + 1;
        if ((rx_counter + 1) == DELAY_FRAMES) begin
          rx_state   <= RX_STATE_IDLE;
          rx_counter <= 0;
          byte_ready <= 1;

        end
      end
    endcase
  end

  // display received byte on leds
  always @(posedge clk) begin
    if (byte_ready) begin
      led <= ~data_in[5:0];
    end
  end

  // TRANSMIT
  reg [3:0] tx_state = 0;
  reg [24:0] tx_counter = 0;  // for clock edge, timing
  reg [7:0] data_out = 0;
  reg tx_pin_register = 1;
  reg [2:0] tx_memory_loc = 0;
  reg [3:0] tx_byte_counter = 0;

  assign uart_tx = tx_pin_register;

  // 12 cells of 8 bit fake memory
  localparam MEMORY_LENGTH = 12;
  reg [7:0] test_memory[MEMORY_LENGTH-1:0];

  initial begin
    test_memory[0]  = "H";
    test_memory[1]  = "e";
    test_memory[2]  = "l";
    test_memory[3]  = "l";
    test_memory[4]  = "o";
    test_memory[5]  = " ";
    test_memory[6]  = "t";
    test_memory[7]  = "h";
    test_memory[8]  = "e";
    test_memory[9]  = "r";
    test_memory[10] = "e";
    test_memory[11] = "!";
  end

  localparam TX_STATE_IDLE = 0;
  localparam TX_STATE_START_BIT = 1;
  localparam TX_STATE_WRITE = 2;
  localparam TX_STATE_STOP_BIT = 3;
  localparam TX_STATE_DEBOUNCE = 4;

  /*
  The idle state waits for the button to be pressed (which will make it go low) at which point we will move to the start bit state. If the button is not pressed we set the uart_tx to be high as in UART we have a high idle state.
  */
  always @(posedge clk) begin
    case (tx_state)
      TX_STATE_IDLE: begin
        if (btn1 == 0) begin
          tx_state <= TX_STATE_START_BIT;
          tx_counter <= 0;
          tx_byte_counter <= 0;
        end else tx_pin_register <= 1;
      end

      /*
      The start bit is a low signal for DELAY_FRAMES, once reached we put the next byte we need to send into dataOut and reset the txBitNumber back to 0.
      */
      TX_STATE_START_BIT: begin
        tx_pin_register <= 0;
        // refactor to:
        // if ((tx_counter < DELAY_FRAMES))
        if ((tx_counter + 1) == DELAY_FRAMES) begin
          tx_state <= TX_STATE_WRITE;
          data_out <= test_memory[tx_byte_counter];
          tx_memory_loc <= 0;
          tx_counter <= 0;
        end else tx_counter <= tx_counter + 1;
      end

      /*
      The write state is very similar, except instead of setting the tx pin to low, we set it to the current bit of the current byte. When the frame is over we check if we are already on the last bit, if so we go to the stop bit state, otherwise we increment the bit number and keep the current state of TX_STATE_WRITE.
      */
      TX_STATE_WRITE: begin
        tx_pin_register <= data_out[tx_memory_loc];
        if ((tx_counter + 1) == DELAY_FRAMES) begin
          if (tx_memory_loc == 3'b111) begin
            tx_state <= TX_STATE_STOP_BIT;
          end else begin
            tx_state <= TX_STATE_WRITE;
            tx_memory_loc <= tx_memory_loc + 1;
          end
          tx_counter <= 0;
        end else tx_counter <= tx_counter + 1;
      end

      /*
      The stop bit is a high output bit, after waiting DELAY_FRAMES we check if there are any other bytes to send, if there are, we go back to send another start bit and the cycle will repeat for the next byte. If not we go to the debounce state.
      */
      TX_STATE_STOP_BIT: begin
        tx_pin_register <= 1;
        if ((tx_counter + 1) == DELAY_FRAMES) begin
          if (tx_byte_counter == MEMORY_LENGTH - 1) begin
            tx_state <= TX_STATE_DEBOUNCE;
          end else begin
            tx_byte_counter <= tx_byte_counter + 1;
            tx_state <= TX_STATE_START_BIT;
          end
          tx_counter <= 0;
        end else tx_counter <= tx_counter + 1;
      end

      TX_STATE_DEBOUNCE: begin
        // 27_000_000 -> 1000 ms delay
        // 5*270_000 -> 50 ms delay
        if (tx_counter == 5 * 270_000) begin
          if (btn1 == 1) tx_state <= TX_STATE_IDLE;
        end else tx_counter <= tx_counter + 1;
      end
    endcase
  end
endmodule

uart/uart_tb.v
// uart testbench example from lushay labs
// mirac gulgonul - 2023

// test module has no inputs/outputs
// instantiates the module to be tested, in this case uart
// and makes the required connections

module test ();
  reg clk = 0;
  reg uart_rx = 1;
  wire uart_tx;
  wire [5:0] led;
  reg btn = 1;

  uart #(8'd8) u (
      clk,
      uart_rx,
      uart_tx,
      led,
      btn
  );

  /*
  The #number (#1) is a special simulation syntax from iverilog that allows
  us to delay something by a certain number of time frames.
  By saying each time interval the clock alternates, we are saying the clock
  cycle is 2 time units (1 high cycle and 1 low cycle is 1 clock cycle).
  So this loop will wait 1 time unit and toggle the clock register.
  */
  always #1 clk = ~clk;

  initial begin
    $display("Starting UART RX");
    $monitor("LED Value %b", led);

    #10 uart_rx = 0;  // start bit
    #16 uart_rx = 1;  // bit 1
    #16 uart_rx = 0;  // bit 2
    #16 uart_rx = 0;  // bit 3
    #16 uart_rx = 0;  // bit 4
    #16 uart_rx = 0;  // bit 5
    #16 uart_rx = 1;  // bit 6
    #16 uart_rx = 1;  // bit 7
    #16 uart_rx = 0;  // bit 8
    #16 uart_rx = 1;  // stop bit
    #1000 $finish;
  end

  initial begin
    $dumpfile("uart.vcd");
    $dumpvars(0, test);
  end

endmodule

uart/uart.vcd
$date
	Mon Jun 26 20:26:01 2023
$end
$version
	Icarus Verilog
$end
$timescale
	1s
$end
$scope module test $end
$var wire 1 ! uart_tx $end
$var wire 6 " led [5:0] $end
$var reg 1 # btn $end
$var reg 1 $ clk $end
$var reg 1 % uart_rx $end
$scope module u $end
$var wire 1 # btn1 $end
$var wire 1 $ clk $end
$var wire 1 % uart_rx $end
$var wire 1 ! uart_tx $end
$var parameter 8 & DELAY_FRAMES $end
$var parameter 32 ' HALF_DELAY_WAIT $end
$var parameter 32 ( MEMORY_LENGTH $end
$var parameter 32 ) RX_STATE_IDLE $end
$var parameter 32 * RX_STATE_READ $end
$var parameter 32 + RX_STATE_READ_WAIT $end
$var parameter 32 , RX_STATE_START_BIT $end
$var parameter 32 - RX_STATE_STOP_BIT $end
$var parameter 32 . TX_STATE_DEBOUNCE $end
$var parameter 32 / TX_STATE_IDLE $end
$var parameter 32 0 TX_STATE_START_BIT $end
$var parameter 32 1 TX_STATE_STOP_BIT $end
$var parameter 32 2 TX_STATE_WRITE $end
$var reg 1 3 byte_ready $end
$var reg 8 4 data_in [7:0] $end
$var reg 8 5 data_out [7:0] $end
$var reg 6 6 led [5:0] $end
$var reg 3 7 rx_bit_number [2:0] $end
$var reg 13 8 rx_counter [12:0] $end
$var reg 4 9 rx_state [3:0] $end
$var reg 4 : tx_byte_counter [3:0] $end
$var reg 25 ; tx_counter [24:0] $end
$var reg 3 < tx_memory_loc [2:0] $end
$var reg 1 = tx_pin_register $end
$var reg 4 > tx_state [3:0] $end
$upscope $end
$upscope $end
$enddefinitions $end
$comment Show the parameter values. $end
$dumpall
b10 2
b11 1
b1 0
b0 /
b100 .
b100 -
b1 ,
b10 +
b11 *
b0 )
b1100 (
b100 '
b1000 &
$end
#0
$dumpvars
b0 >
1=
b0 <
b0 ;
b0 :
b0 9
b0 8
b0 7
bx 6
b0 5
b0 4
03
1%
0$
1#
bx "
1!
$end
#1
1$
#2
0$
#3
1$
#4
0$
#5
1$
#6
0$
#7
1$
#8
0$
#9
1$
#10
0$
0%
#11
b1 8
b1 9
1$
#12
0$
#13
b10 8
1$
#14
0$
#15
b11 8
1$
#16
0$
#17
b100 8
1$
#18
0$
#19
b1 8
b10 9
1$
#20
0$
#21
b10 8
1$
#22
0$
#23
b11 8
1$
#24
0$
#25
b100 8
1$
#26
0$
1%
#27
b101 8
1$
#28
0$
#29
b110 8
1$
#30
0$
#31
b111 8
1$
#32
0$
#33
b11 9
b1000 8
1$
#34
0$
#35
b10 9
b1 7
b10000000 4
b1 8
1$
#36
0$
#37
b10 8
1$
#38
0$
#39
b11 8
1$
#40
0$
#41
b100 8
1$
#42
0$
0%
#43
b101 8
1$
#44
0$
#45
b110 8
1$
#46
0$
#47
b111 8
1$
#48
0$
#49
b11 9
b1000 8
1$
#50
0$
#51
b10 9
b10 7
b1000000 4
b1 8
1$
#52
0$
#53
b10 8
1$
#54
0$
#55
b11 8
1$
#56
0$
#57
b100 8
1$
#58
0$
#59
b101 8
1$
#60
0$
#61
b110 8
1$
#62
0$
#63
b111 8
1$
#64
0$
#65
b11 9
b1000 8
1$
#66
0$
#67
b10 9
b11 7
b100000 4
b1 8
1$
#68
0$
#69
b10 8
1$
#70
0$
#71
b11 8
1$
#72
0$
#73
b100 8
1$
#74
0$
#75
b101 8
1$
#76
0$
#77
b110 8
1$
#78
0$
#79
b111 8
1$
#80
0$
#81
b11 9
b1000 8
1$
#82
0$
#83
b10 9
b100 7
b10000 4
b1 8
1$
#84
0$
#85
b10 8
1$
#86
0$
#87
b11 8
1$
#88
0$
#89
b100 8
1$
#90
0$
#91
b101 8
1$
#92
0$
#93
b110 8
1$
#94
0$
#95
b111 8
1$
#96
0$
#97
b11 9
b1000 8
1$
#98
0$
#99
b10 9
b101 7
b1000 4
b1 8
1$
#100
0$
#101
b10 8
1$
#102
0$
#103
b11 8
1$
#104
0$
#105
b100 8
1$
#106
0$
1%
#107
b101 8
1$
#108
0$
#109
b110 8
1$
#110
0$
#111
b111 8
1$
#112
0$
#113
b11 9
b1000 8
1$
#114
0$
#115
b10 9
b110 7
b10000100 4
b1 8
1$
#116
0$
#117
b10 8
1$
#118
0$
#119
b11 8
1$
#120
0$
#121
b100 8
1$
#122
0$
#123
b101 8
1$
#124
0$
#125
b110 8
1$
#126
0$
#127
b111 8
1$
#128
0$
#129
b11 9
b1000 8
1$
#130
0$
#131
b10 9
b111 7
b11000010 4
b1 8
1$
#132
0$
#133
b10 8
1$
#134
0$
#135
b11 8
1$
#136
0$
#137
b100 8
1$
#138
0$
0%
#139
b101 8
1$
#140
0$
#141
b110 8
1$
#142
0$
#143
b111 8
1$
#144
0$
#145
b11 9
b1000 8
1$
#146
0$
#147
b100 9
b0 7
b1100001 4
b1 8
1$
#148
0$
#149
b10 8
1$
#150
0$
#151
b11 8
1$
#152
0$
#153
b100 8
1$
#154
0$
1%
#155
b101 8
1$
#156
0$
#157
b110 8
1$
#158
0$
#159
b111 8
1$
#160
0$
#161
13
b0 9
b0 8
1$
#162
0$
#163
b11110 "
b11110 6
1$
